legallint/__init__.py
legallint/exceptions.py
legallint/license/__init__.py
legallint/license/licenses.json
legallint/license/resources.txt
legallint/license/update.py
legallint/lint.py
legallint/plugin.py
legallint/plugins/__init__.py
legallint/plugins/for_node.py
legallint/plugins/for_python.py
legallint/scripts/__init__.py
legallint/scripts/legallint_tool.py
legallint/utils.py
legallint-1.1.0.dist-info/LICENSE
legallint-1.1.0.dist-info/METADATA
legallint-1.1.0.dist-info/WHEEL
legallint-1.1.0.dist-info/entry_points.txt
legallint-1.1.0.dist-info/RECORD
