Metadata-Version: 2.1
Name: legallint
Version: 1.1.0
Summary: LegalLint: A Multi-Language License Compliance Linter
License: Apache-2.0
Author: Kiran Kumar Kotari
Author-email: kirankotari@live.com
Requires-Python: >=3.8,<4.0
Classifier: License :: OSI Approved :: Apache Software License
Classifier: Programming Language :: Python :: 3
Classifier: Programming Language :: Python :: 3.8
Classifier: Programming Language :: Python :: 3.9
Classifier: Programming Language :: Python :: 3.10
Classifier: Programming Language :: Python :: 3.11
Classifier: Programming Language :: Python :: 3.12
Requires-Dist: pyyaml (>=6.0.2,<7.0.0)
Requires-Dist: requests (>=2.32.3,<3.0.0)
Requires-Dist: toml (>=0.10.2,<0.11.0)
